openbb/__init__.py
theobb-1.0.0.dist-info/LICENSE
theobb-1.0.0.dist-info/METADATA
theobb-1.0.0.dist-info/WHEEL
theobb-1.0.0.dist-info/RECORD
