Metadata-Version: 2.1
Name: theobb
Version: 1.0.0
Summary: The obb and nothing else.
Author: Theodore
Author-email: aptekarev@gmail.com
Requires-Python: >=3.9,<3.13
Classifier: Programming Language :: Python :: 3
Classifier: Programming Language :: Python :: 3.9
Classifier: Programming Language :: Python :: 3.10
Classifier: Programming Language :: Python :: 3.11
Classifier: Programming Language :: Python :: 3.12
Requires-Dist: openbb-core (>=1.2.9,<2.0.0)
